samcell_napari/__init__.py
samcell_napari/__main__.py
samcell_napari/_dock_widget.py
samcell_napari/_sample_data.py
samcell_napari/icon.svg
samcell_napari/metrics.py
samcell_napari/model.py
samcell_napari/napari.yaml
samcell_napari/pipeline.py
samcell_napari/slidingWindow.py
samcell_napari-1.1.3.dist-info/licenses/LICENSE
samcell_napari-1.1.3.dist-info/METADATA
samcell_napari-1.1.3.dist-info/WHEEL
samcell_napari-1.1.3.dist-info/entry_points.txt
samcell_napari-1.1.3.dist-info/top_level.txt
samcell_napari-1.1.3.dist-info/RECORD
