Metadata-Version: 2.4
Name: samcell-napari
Version: 1.1.3
Summary: A napari plugin for cell segmentation with SAMCell 1.0
Home-page: https://github.com/saahilsanganeriya/samcell-napari
Author: Saahil Sanganeriya
Author-email: saahilsanganeria666@gmail.com
Project-URL: Bug Tracker, https://github.com/saahilsanganeriya/samcell-napari/issues
Classifier: Programming Language :: Python :: 3
Classifier: Programming Language :: Python :: 3.8
Classifier: Programming Language :: Python :: 3.9
Classifier: Programming Language :: Python :: 3.10
Classifier: License :: OSI Approved :: MIT License
Classifier: Operating System :: OS Independent
Classifier: Framework :: napari
Classifier: Intended Audience :: Science/Research
Classifier: Topic :: Scientific/Engineering :: Bio-Informatics
Classifier: Topic :: Scientific/Engineering :: Image Processing
Requires-Python: >=3.8
License-File: LICENSE
Requires-Dist: napari>=0.4.14
Requires-Dist: numpy>=1.21.0
Requires-Dist: torch>=1.9
Requires-Dist: transformers>=4.26.0
Requires-Dist: scikit-image>=0.19.0
Requires-Dist: opencv-python>=4.5.0
Requires-Dist: scipy>=1.7.0
Requires-Dist: pandas>=1.3.0
Requires-Dist: tqdm>=4.60.0
Requires-Dist: safetensors>=0.3.0
Requires-Dist: timm>=0.6.0
Requires-Dist: openpyxl>=3.0.0
Provides-Extra: safetensors
Requires-Dist: safetensors>=0.3.0; extra == "safetensors"
Provides-Extra: dev
Requires-Dist: black; extra == "dev"
Requires-Dist: pytest; extra == "dev"
Requires-Dist: pytest-cov; extra == "dev"
Dynamic: license-file
